{
  "consumer": {
    "name": "ExampleOpenAPISpecConsumer"
  },
  "provider": {
    "name": "ExampleOpenAPISpecProvider"
  },
  "interactions": [
    {
      "description": "/my-mappings get",
      "providerStates": [
        {
          "name": "/my-mappings get"
        }
      ],
      "request": {
        "method": "GET",
        "path": "/my-mappings"
      },
      "response": {
        "status": 200,
        "headers": {
          "Content-Type": "application/json"
        },
        "body": [
          {
            "userUUID": "fc1a7789-7467-4899-b569-6adc1895e41c",
            "userName": "72XnVATO2K",
            "issuer": "hRFtd6STpp",
            "claimName": "3n7BtVRLAr",
            "claimValue": "HhtwJHxeWS"
          },
          {
            "userUUID": "5beea725-9612-4317-bbd9-01ac6d7144cb",
            "userName": "02eQkz7Yvc",
            "issuer": "gvJKOfaKWJ",
            "claimName": "aHnTJDA9ks",
            "claimValue": "c4oPEHDOSV"
          },
          {
            "userUUID": "c4f5a4c0-66d0-4582-ad2a-19ea465d620f",
            "userName": "EzMBG5rRy9",
            "issuer": "UAADlqDoeD",
            "claimName": "hTcwI6wwNR",
            "claimValue": "8qPzUiuv3k"
          }
        ]
      }
    },
    {
      "description": "/my-mappings post",
      "providerStates": [
        {
          "name": "/my-mappings post"
        }
      ],
      "request": {
        "method": "POST",
        "path": "/my-mappings",
        "headers": {
          "Content-Type": "application/json"
        },
        "body": {
          "userUUID": "fc1a7789-7467-4899-b569-6adc1895e41c",
          "userName": "72XnVATO2K",
          "issuer": "hRFtd6STpp",
          "claimName": "3n7BtVRLAr",
          "claimValue": "HhtwJHxeWS"
        }
      },
      "response": {
        "status": 200
      }
    },
    {
      "description": "/my-mappings delete",
      "providerStates": [
        {
          "name": "/my-mappings delete"
        }
      ],
      "request": {
        "method": "DELETE",
        "path": "/my-mappings",
        "headers": {
          "Content-Type": "application/json"
        },
        "body": {
          "userUUID": "fc1a7789-7467-4899-b569-6adc1895e41c",
          "userName": "72XnVATO2K",
          "issuer": "hRFtd6STpp",
          "claimName": "3n7BtVRLAr",
          "claimValue": "HhtwJHxeWS"
        }
      },
      "response": {
        "status": 200
      }
    },
    {
      "description": "/my-objects get",
      "providerStates": [
        {
          "name": "/my-objects get"
        }
      ],
      "request": {
        "method": "GET",
        "path": "/my-objects"
      },
      "response": {
        "status": 200,
        "headers": {
          "Content-Type": "application/json"
        },
        "body": [
          {
            "valueOne": "mhZ7yW8Qd3",
            "valueTwo": -95.95,
            "valueThree": 13,
            "valueFour": true,
            "valueFive": {
              "subValueOne": "tJy9Tkqor4",
              "subValueTwo": 39
            }
          },
          {
            "valueOne": "OPGz7C089i",
            "valueTwo": -52.56,
            "valueThree": 32,
            "valueFour": true,
            "valueFive": {
              "subValueOne": "fvZGAOM49J",
              "subValueTwo": 68
            }
          },
          {
            "valueOne": "FcBLScVlAE",
            "valueTwo": -27.52,
            "valueThree": 16,
            "valueFour": true,
            "valueFive": {
              "subValueOne": "hUCf7eCzxJ",
              "subValueTwo": 9
            }
          }
        ]
      }
    },
    {
      "description": "/my-objects post",
      "providerStates": [
        {
          "name": "/my-objects post"
        }
      ],
      "request": {
        "method": "POST",
        "path": "/my-objects",
        "headers": {
          "Content-Type": "application/json"
        },
        "body": {
          "valueOne": "mhZ7yW8Qd3",
          "valueTwo": -95.95,
          "valueThree": 13,
          "valueFour": true,
          "valueFive": {
            "subValueOne": "tJy9Tkqor4",
            "subValueTwo": 39
          }
        }
      },
      "response": {
        "status": 200
      }
    },
    {
      "description": "/my-objects delete",
      "providerStates": [
        {
          "name": "/my-objects delete"
        }
      ],
      "request": {
        "method": "DELETE",
        "path": "/my-objects",
        "headers": {
          "Content-Type": "application/json"
        },
        "body": {
          "valueOne": "mhZ7yW8Qd3",
          "valueTwo": -95.95,
          "valueThree": 13,
          "valueFour": true,
          "valueFive": {
            "subValueOne": "tJy9Tkqor4",
            "subValueTwo": 39
          }
        }
      },
      "response": {
        "status": 200
      }
    },
    {
      "description": "/important-things get",
      "providerStates": [
        {
          "name": "/important-things get"
        }
      ],
      "request": {
        "method": "GET",
        "path": "/important-things"
      },
      "response": {
        "status": 200,
        "headers": {
          "Content-Type": "application/json"
        },
        "body": "4aaT5N3d7u"
      }
    },
    {
      "description": "/important-things post",
      "providerStates": [
        {
          "name": "/important-things post"
        }
      ],
      "request": {
        "method": "POST",
        "path": "/important-things",
        "headers": {
          "Content-Type": "application/json"
        },
        "body": -34.4
      },
      "response": {
        "status": 200
      }
    },
    {
      "description": "/important-things delete",
      "providerStates": [
        {
          "name": "/important-things delete"
        }
      ],
      "request": {
        "method": "DELETE",
        "path": "/important-things",
        "headers": {
          "Content-Type": "application/json"
        },
        "body": -56.56
      },
      "response": {
        "status": 200,
        "headers": {
          "Content-Type": "application/json"
        },
        "body": {
          "id": 13,
          "myObject": {
            "userUUID": "fc1a7789-7467-4899-b569-6adc1895e41c",
            "userName": "72XnVATO2K",
            "issuer": "hRFtd6STpp",
            "claimName": "3n7BtVRLAr",
            "claimValue": "HhtwJHxeWS"
          }
        }
      }
    }
  ],
  "metadata": {
    "pactSpecification": {
      "version": "2.0.0"
    }
  }
}